README
setup.py
cvc/DroidSansMono.ttf
cvc/__init__.py
cvc/__main__.py
cvc/converter.py
cvc.egg-info/PKG-INFO
cvc.egg-info/SOURCES.txt
cvc.egg-info/dependency_links.txt
cvc.egg-info/entry_points.txt
cvc.egg-info/requires.txt
cvc.egg-info/top_level.txt