Metadata-Version: 2.1
Name: cvc
Version: 0.8.0
Summary: Convert video to character art animation.
Home-page: https://github.com/Alston-Trevelyan/cvc
Author: Alston Trevelyan
Author-email: 2841563908@qq.com
Maintainer: Alston Trevelyan
Maintainer-email: 2841563908@qq.com
License: UNKNOWN
Platform: UNKNOWN
Classifier: Programming Language :: Python :: 3
Classifier: License :: OSI Approved :: MIT License
Classifier: Operating System :: OS Independent
